odoo9_addon_account_draft_invoice_print-9.0.1.0.0-py2.7-nspkg.pth
odoo_addons/account_draft_invoice_print/invoice_view.xml
odoo_addons/account_draft_invoice_print/__openerp__.py
odoo_addons/account_draft_invoice_print/__init__.py
odoo_addons/account_draft_invoice_print/README.rst
odoo_addons/account_draft_invoice_print/i18n/account_draft_invoice_print.pot
odoo9_addon_account_draft_invoice_print-9.0.1.0.0.dist-info/top_level.txt
odoo9_addon_account_draft_invoice_print-9.0.1.0.0.dist-info/WHEEL
odoo9_addon_account_draft_invoice_print-9.0.1.0.0.dist-info/RECORD
odoo9_addon_account_draft_invoice_print-9.0.1.0.0.dist-info/metadata.json
odoo9_addon_account_draft_invoice_print-9.0.1.0.0.dist-info/DESCRIPTION.rst
odoo9_addon_account_draft_invoice_print-9.0.1.0.0.dist-info/METADATA
odoo9_addon_account_draft_invoice_print-9.0.1.0.0.dist-info/namespace_packages.txt
